{
    "Features": {
        "MetricsReportingEnabled": false,
        "BraveDeAmpEnabled": true,
        "BraveDebouncingEnabled": true,
        "BraveTrackingQueryParametersFilteringEnabled": true,
        "BraveRewardsDisabled": true,
        "BraveWalletDisabled": true,
        "BraveVPNDisabled": true,
        "BraveAIChatEnabled": false,
        "BraveNewsDisabled": true,
        "BraveTalkDisabled": true,
        "BravePlaylistEnabled": false,
        "IPFSEnabled": false,
        "BackgroundModeEnabled": false,
        "ShoppingListEnabled": false,
        "DefaultBrowserSettingEnabled": false,
        "BraveWaybackMachineEnabled": false
    },
    "DnsMode": "automatic"
}
